ifile/__init__.py
ifile/cli.py
ifile/default_config.ini
ifile/default_supervisord.conf
ifile/exception.py
ifile/services.py
ifile/setting.py
ifile/utils.py
ifile/version.py
ifile/api/__init__.py
ifile/api/client.py
ifile/api/errors.py
ifile/api/file.py
ifile/api/routes.py
ifile/api/services.py
ifile/api/task.py
ifile/apps/__init__.py
ifile/apps/beat.py
ifile/apps/task.py
ifile/apps/web.py
ifile/client/__init__.py
ifile/client/api.py
ifile/client/heartbeat.py
ifile/client/services.py
ifile/client/rpc/__init__.py
ifile/client/rpc/client_pb2.py
ifile/client/rpc/client_pb2_grpc.py
ifile/common/__init__.py
ifile/common/constant.py
ifile/db/__init__.py
ifile/db/base.py
ifile/db/sqlalchemy/__init__.py
ifile/db/sqlalchemy/api.py
ifile/db/sqlalchemy/models.py
ifile/db/sqlalchemy/session.py
ifile/storage/__init__.py
ifile/storage/api.py
ifile/storage/base.py
ifile/storage/disk.py
ifile/storage/mongo.py
ifile-0.9.1.2.dist-info/LICENSE
ifile-0.9.1.2.dist-info/METADATA
ifile-0.9.1.2.dist-info/WHEEL
ifile-0.9.1.2.dist-info/entry_points.txt
ifile-0.9.1.2.dist-info/top_level.txt
ifile-0.9.1.2.dist-info/RECORD
