Metadata-Version: 2.1
Name: ifile
Version: 0.9.1.2
Summary: this is a file mange tool
Home-page: https://github.com/Glf9832/ifile
Author: Greene
Author-email: Glf9832@163.com
License: UNKNOWN
Platform: UNKNOWN
Requires-Python: >=3.6
Requires-Dist: Click
Requires-Dist: SQLAlchemy (==1.3.5)
Requires-Dist: Flask (==1.0.3)
Requires-Dist: eventlet (==0.25.0)
Requires-Dist: pymysql (==0.9.3)
Requires-Dist: pymongo (==3.9.0)
Requires-Dist: gunicorn (==19.9.0)
Requires-Dist: pyftpdlib (==1.5.5)
Requires-Dist: grpcio (==1.26.0)
Requires-Dist: protobuf (==3.11.2)
Requires-Dist: psycopg2-binary (==2.8.4)
Requires-Dist: sentry-sdk (==0.10.2)
